[
  {
    "Resource ID": 1,
    "Resource Type": "Flashcards",
    "Resource Title": "Cell Biology",
    "Study Level": "GCSE",
    "Subject": "Biology",
    "Exam Board": "AQA",
    "Link": "https://quizlet.com/gb/256416471/1-aqa-gcse-biology-cell-biology-flash-cards/",
    "Resource Author": "",
    "Average Rating": 5,
    "Resource Description": "A set of flashcards to help revise topics like prokaryotic/eukaryotic cells, mitosis, microscopes and transport in cells."
  },
  {
    "Resource ID": 2,
    "Resource Type": "Flashcards",
    "Resource Title": "Parts of the Processor",
    "Study Level": "GCSE",
    "Subject": "Computer Science",
    "Exam Board": "OCR",
    "Link": "https://quizlet.com/gb/914101722/jekyll-hyde-key-terms-flash-cards/?i=3aekab&x=1jqt",
    "Resource Author": "Megan Hudson",
    "Average Rating": 5,
    "Resource Description": "A helpful set of flashcards to understand CPU architecture and the role of different processor components."
  },
  {
    "Resource ID": 3,
    "Resource Type": "Flashcards",
    "Resource Title": "Factors affecting the CPU",
    "Study Level": "GCSE",
    "Subject": "Computer Science",
    "Exam Board": "OCR",
    "Link": "https://quizlet.com/gb/950747571/factors-affecting-cpu-flash-cards/?x=1jqU&i=4j3p4y",
    "Resource Author": "Megan Hudson",
    "Average Rating": 5,
    "Resource Description": "Useful for revising the impact of different hardware features on processing speed."
  },
  {
    "Resource ID": 4,
    "Resource Type": "Flashcards",
    "Resource Title": "Von Neuman Architecture",
    "Study Level": "GCSE",
    "Subject": "Computer Science",
    "Exam Board": "OCR",
    "Link": "https://quizlet.com/gb/950760044/von-neuman-and-harvard-flash-cards/?x=1jqU&i=4j3p4y",
    "Resource Author": "Megan Hudson",
    "Average Rating": 5,
    "Resource Description": "Ideal for understanding the structure and function of traditional computer systems in GCSE CS."
  },
  {
    "Resource ID": 5,
    "Resource Type": "Flashcards",
    "Resource Title": "Understanding FDE Cycles",
    "Study Level": "GCSE",
    "Subject": "Computer Science",
    "Exam Board": "OCR",
    "Link": "https://quizlet.com/gb/950734396/understanding-the-fetch-execute-cycle-in-computing-flash-cards/?x=1jqU&i=4j3p4y",
    "Resource Author": "Megan Hudson",
    "Average Rating": 5,
    "Resource Description": "Great for revising how instructions are processed by a CPU step by step."
  },
  {
    "Resource ID": 6,
    "Resource Type": "Flashcards",
    "Resource Title": "GPUs",
    "Study Level": "GCSE",
    "Subject": "Computer Science",
    "Exam Board": "OCR",
    "Link": "https://quizlet.com/gb/955021553/gpus-flash-cards/?x=1jqU&i=4j3p4y",
    "Resource Author": "Megan Hudson",
    "Average Rating": 5,
    "Resource Description": "A concise guide to the role and advantages of graphics processing units."
  },
  {
    "Resource ID": 7,
    "Resource Type": "Essay Plans",
    "Resource Title": "Macbeth",
    "Study Level": "GCSE",
    "Subject": "English Literature",
    "Exam Board": "Edexcel",
    "Link": "https://docs.google.com/document/d/1bIkpZU7L6SBGEbjXsJN5FlXJ-Uxax4jfSp0OySsG-xY/edit?usp=sharing",
    "Resource Author": "Abdul Rehman",
    "Average Rating": 5,
    "Resource Description": "Structured paragraph plans exploring ambition, guilt, masculinity and more in Macbeth."
  },
  {
    "Resource ID": 8,
    "Resource Type": "Essay Plans",
    "Resource Title": "An Inspector Calls",
    "Study Level": "GCSE",
    "Subject": "English Literature",
    "Exam Board": "Edexcel",
    "Link": "https://docs.google.com/document/d/1uCUb0G4HAlM_rb5zOD4KfwrHpRv3WgGQgEMJbq1gVY8/edit?usp=sharing",
    "Resource Author": "Abdul Rehman",
    "Average Rating": 5,
    "Resource Description": "Great resource for planning essays on Priestley’s message, characters and dramatic techniques."
  },
  {
    "Resource ID": 9,
    "Resource Type": "Essay Plans",
    "Resource Title": "Jekyll & Hyde",
    "Study Level": "GCSE",
    "Subject": "English Literature",
    "Exam Board": "Edexcel",
    "Link": "https://docs.google.com/document/d/1OuPpi016ZaQZnBKrI8V180uxkUAnsfIU6AvFa1e9vms/edit?usp=sharing",
    "Resource Author": "Abdul Rehman",
    "Average Rating": 5,
    "Resource Description": "Breakdown of key quotes, essay structures and theme analyses."
  },
  {
    "Resource ID": 10,
    "Resource Type": "Essay Plans",
    "Resource Title": "Relationships Poetry Anthology",
    "Study Level": "GCSE",
    "Subject": "English Literature",
    "Exam Board": "Edexcel",
    "Link": "https://docs.google.com/document/d/1RIQs76ZHDnLm_xOTGJ0sZnAb3tdyIsEydWOzLMo6ICo/edit?usp=sharing",
    "Resource Author": "Abdul Rehman",
    "Average Rating": 5,
    "Resource Description": "Helps with comparative analysis, thematic links, and context for each poem."
  },
  {
    "Resource ID": 11,
    "Resource Type": "Flashcards",
    "Resource Title": "Jekyll & Hyde Quotes",
    "Study Level": "GCSE",
    "Subject": "English Literature",
    "Exam Board": "Edexcel",
    "Link": "https://quizlet.com/gb/867349540/flash-cards/?funnelUUID=94117d0c-314e-4e2f-93cd-7d7010f27111",
    "Resource Author": "Abdul Rehman",
    "Average Rating": 5,
    "Resource Description": "Useful for memorising key quotations and linking them to themes and context."
  },
  {
    "Resource ID": 12,
    "Resource Type": "Flashcards",
    "Resource Title": "Jekyll & Hyde Key Terms",
    "Study Level": "GCSE",
    "Subject": "English Literature",
    "Exam Board": "Edexcel",
    "Link": "https://quizlet.com/gb/914101722/jekyll-hyde-key-terms-flash-cards/?i=3aekab&x=1jqt",
    "Resource Author": "Abdul Rehman",
    "Average Rating": 5,
    "Resource Description": "Helps reinforce understanding of analytical vocabulary and techniques."
  },
  {
    "Resource ID": 13,
    "Resource Type": "Flashcards",
    "Resource Title": "An Inspector Calls Quotes",
    "Study Level": "GCSE",
    "Subject": "English Literature",
    "Exam Board": "Edexcel",
    "Link": "https://quizlet.com/gb/903311960/aic-quotes-essay-plans-flash-cards/?i=3aekab&x=1jqt",
    "Resource Author": "Abdul Rehman",
    "Average Rating": 5,
    "Resource Description": "Ideal for quote memorisation and analysis for exam preparation."
  },
  {
    "Resource ID": 14,
    "Resource Type": "Flashcards",
    "Resource Title": "Macbeth Key Quotes",
    "Study Level": "GCSE",
    "Subject": "English Literature",
    "Exam Board": "Edexcel",
    "Link": "https://quizlet.com/gb/893918569/macbeth-quotes-analysis-flash-cards/?i=3aekab&x=1jqt",
    "Resource Author": "Abdul Rehman",
    "Average Rating": 5,
    "Resource Description": "Excellent revision tool for embedding crucial quotes."
  },
  {
    "Resource ID": 15,
    "Resource Type": "Notes",
    "Resource Title": "Physics Notes: Topic 1 Energy",
    "Study Level": "GCSE",
    "Subject": "Physics",
    "Exam Board": "AQA",
    "Link": "https://drive.google.com/file/d/1RQqeLIJtSHdERYNeVh7eQsCdsxhNtAI7/view?usp=sharing",
    "Resource Author": "Community Member",
    "Average Rating": 5,
    "Resource Description": "A set of handwritten notes for AQA Physics."
  },
  {
    "Resource ID": 16,
    "Resource Type": "Notes",
    "Resource Title": "Physics Notes: Topic 2 Electricity",
    "Study Level": "GCSE",
    "Subject": "Physics",
    "Exam Board": "AQA",
    "Link": "https://drive.google.com/file/d/1Hl4rI48QYFUak-M5b2feUzbBPuLjBBuL/view?usp=sharing",
    "Resource Author": "Community Member",
    "Average Rating": 5,
    "Resource Description": "A set of handwritten notes for AQA Physics."
  },
  {
    "Resource ID": 17,
    "Resource Type": "Notes",
    "Resource Title": "Physics Notes: Topic 3 The Particle Model of Matter",
    "Study Level": "GCSE",
    "Subject": "Physics",
    "Exam Board": "AQA",
    "Link": "https://drive.google.com/file/d/1KHLbQ00J-JHJ8kp1YyjNH1xUcb8L2ipR/view?usp=sharing",
    "Resource Author": "Community Member",
    "Average Rating": 5,
    "Resource Description": "A set of handwritten notes for AQA Physics."
  },
  {
    "Resource ID": 18,
    "Resource Type": "Notes",
    "Resource Title": "Physics Notes: Topic 4 Atomic Structure",
    "Study Level": "GCSE",
    "Subject": "Physics",
    "Exam Board": "AQA",
    "Link": "https://drive.google.com/file/d/1FXizu9gDqki65iSNekGP_Gv5TyNSPkrQ/view?usp=sharing",
    "Resource Author": "Community Member",
    "Average Rating": 5,
    "Resource Description": "A set of handwritten notes for AQA Physics."
  },
  {
    "Resource ID": 19,
    "Resource Type": "Essay Plans",
    "Resource Title": "Relationships Poetry Anthology",
    "Study Level": "GCSE",
    "Subject": "English LIterature",
    "Exam Board": "Edexcel",
    "Link": "https://docs.google.com/document/d/1o8fCw_ucmVQTx3OIXg9Fr44Y8olAzKWP/edit?usp=sharing&ouid=114847739282607374210&rtpof=true&sd=true",
    "Resource Author": "Rahul Madavaneri",
    "Average Rating": 5,
    "Resource Description": "An in-depth resource for the Relationships Poetry Anthology."
  },
  {
    "Resource ID": 20,
    "Resource Type": "Notes",
    "Resource Title": "Geography Case Studies",
    "Study Level": "GCSE",
    "Subject": "Geography",
    "Exam Board": "OCR B",
    "Link": "https://docs.google.com/document/d/1wfelji8IvSIfShvOgareFUoVP4J9-NoD/edit?usp=sharing&ouid=114847739282607374210&rtpof=true&sd=true",
    "Resource Author": "Rahul Madavaneri",
    "Average Rating": 5,
    "Resource Description": "In depth notes for OCR B Geography case studies."
  }
]